mieaa/__init__.py
mieaa/_version.py
mieaa/mieaa_cli.py
mieaa/mieaa_wrapper.py
mieaa-0.3.0.dist-info/LICENSE
mieaa-0.3.0.dist-info/METADATA
mieaa-0.3.0.dist-info/WHEEL
mieaa-0.3.0.dist-info/entry_points.txt
mieaa-0.3.0.dist-info/top_level.txt
mieaa-0.3.0.dist-info/RECORD
