Metadata-Version: 2.1
Name: mieaa
Version: 0.3.0
Summary: miEAA Command Line Interface and API
Home-page: https://www.ccb.uni-saarland.de/mieaa2
Author: Jeffrey Solomon
Maintainer: Chair for Clinical Bioinformatics at Saarland University
Maintainer-email: ccb.unisb@gmail.com
License: MIT
Download-URL: https://pypi.org/project/mieaa/#files
Project-URL: Bug Tracker, https://github.com/Xethic/miEAA-API/issues
Project-URL: Documentation, https://mieaa.readthedocs.io/en/latest/
Project-URL: Source Code, https://github.com/Xethic/miEAA-API
Keywords: mirna bioinformatics
Platform: UNKNOWN
Classifier: Development Status :: 4 - Beta
Classifier: License :: OSI Approved :: MIT License
Classifier: Programming Language :: Python :: 3
Classifier: Programming Language :: Python :: 3.5
Classifier: Programming Language :: Python :: 3.6
Classifier: Programming Language :: Python :: 3.7
Classifier: Intended Audience :: Science/Research
Classifier: Natural Language :: English
Classifier: Topic :: Scientific/Engineering :: Bio-Informatics
Requires-Python: >=3.5.*, <4
Requires-Dist: requests (>=2.19.*)
